qctrlsphinxtheme/__init__.py
qctrlsphinxtheme/breadcrumbs.html
qctrlsphinxtheme/footer.html
qctrlsphinxtheme/layout.html
qctrlsphinxtheme/searchbox.html
qctrlsphinxtheme/static/css/docsearch.css
qctrlsphinxtheme/static/css/qctrlsphinxtheme.css
qctrlsphinxtheme/static/favicon.ico
qctrlsphinxtheme/static/img/q-ctrl-icon-180.png
qctrlsphinxtheme/static/img/q-ctrl-icon-192.png
qctrlsphinxtheme/static/img/q-ctrl-icon-512.png
qctrlsphinxtheme/static/img/q-ctrl-icon.svg
qctrlsphinxtheme/static/img/q-ctrl-logo.svg
qctrlsphinxtheme/static/img/social/image.jpg
qctrlsphinxtheme/static/js/qctrlsphinxtheme.js_t
qctrlsphinxtheme/static/manifest.webmanifest
qctrlsphinxtheme/static/pygments.css
qctrlsphinxtheme/theme.conf
qctrl_sphinx_theme-2.1.4.dist-info/LICENSE
qctrl_sphinx_theme-2.1.4.dist-info/METADATA
qctrl_sphinx_theme-2.1.4.dist-info/WHEEL
qctrl_sphinx_theme-2.1.4.dist-info/entry_points.txt
qctrl_sphinx_theme-2.1.4.dist-info/RECORD
